<annotation>
  <object>
    <name>Vehicle</name>
    <bndbox>
      <xmin>747</xmin>
      <ymin>490</ymin>
      <xmax>850</xmax>
      <ymax>518</ymax>
    </bndbox>
    <confidence>0.285603</confidence>
  </object>
  <object>
    <name>Vehicle</name>
    <bndbox>
      <xmin>622</xmin>
      <ymin>549</ymin>
      <xmax>654</xmax>
      <ymax>584</ymax>
    </bndbox>
    <confidence>0.674847</confidence>
  </object>
  <object>
    <name>Vehicle</name>
    <bndbox>
      <xmin>651</xmin>
      <ymin>522</ymin>
      <xmax>735</xmax>
      <ymax>589</ymax>
    </bndbox>
    <confidence>0.893231</confidence>
  </object>
  <object>
    <name>TrafficSign</name>
    <bndbox>
      <xmin>889</xmin>
      <ymin>186</ymin>
      <xmax>1042</xmax>
      <ymax>268</ymax>
    </bndbox>
    <confidence>0.902241</confidence>
  </object>
  <object>
    <name>Vehicle</name>
    <bndbox>
      <xmin>895</xmin>
      <ymin>500</ymin>
      <xmax>955</xmax>
      <ymax>574</ymax>
    </bndbox>
    <confidence>0.90461</confidence>
  </object>
  <object>
    <name>Vehicle</name>
    <bndbox>
      <xmin>183</xmin>
      <ymin>536</ymin>
      <xmax>341</xmax>
      <ymax>622</ymax>
    </bndbox>
    <confidence>0.958733</confidence>
  </object>
  <object>
    <name>Vehicle</name>
    <bndbox>
      <xmin>729</xmin>
      <ymin>512</ymin>
      <xmax>895</xmax>
      <ymax>630</ymax>
    </bndbox>
    <confidence>0.973127</confidence>
  </object>
</annotation>
