<annotation>
  <object>
    <name>Vehicle</name>
    <bndbox>
      <xmin>910</xmin>
      <ymin>519</ymin>
      <xmax>969</xmax>
      <ymax>546</ymax>
    </bndbox>
    <confidence>0.453544</confidence>
  </object>
  <object>
    <name>TrafficSign</name>
    <bndbox>
      <xmin>1001</xmin>
      <ymin>393</ymin>
      <xmax>1028</xmax>
      <ymax>419</ymax>
    </bndbox>
    <confidence>0.87665</confidence>
  </object>
  <object>
    <name>Vehicle</name>
    <bndbox>
      <xmin>894</xmin>
      <ymin>531</ymin>
      <xmax>974</xmax>
      <ymax>594</ymax>
    </bndbox>
    <confidence>0.914384</confidence>
  </object>
  <object>
    <name>Vehicle</name>
    <bndbox>
      <xmin>604</xmin>
      <ymin>439</ymin>
      <xmax>804</xmax>
      <ymax>645</ymax>
    </bndbox>
    <confidence>0.960797</confidence>
  </object>
</annotation>
