<?xml version="1.0" encoding="UTF-8"?>
<annotation>
  <ver>v001_1</ver>
  <folder>1</folder>
  <filename>1_20200720_102833_006330.jpg</filename>
  <path>C:\Users\KATECH-02\Desktop\검수(이수원)_성선영_1\20200720_원주_손지영\20200720_102833\1\</path>
  <source>
    <database>KATECH_DB</database>
  </source>
  <size>
    <width>1920</width>
    <height>1080</height>
    <depth>3</depth>
  </size>
  <segmented>0</segmented>
  <index_max>16</index_max>
  <object>
    <name>RoadMark_Crosswalk</name>
    <pose>Unspecified</pose>
    <truncated>0</truncated>
    <difficult>0</difficult>
    <bndbox>
      <xmin>0</xmin>
      <ymin>877</ymin>
      <xmax>1415</xmax>
      <ymax>991</ymax>
    </bndbox>
    <index>4</index>
    <review_code>C_v001</review_code>
  </object>
  <object>
    <name>RoadMark_Crosswalk</name>
    <pose>Unspecified</pose>
    <truncated>0</truncated>
    <difficult>0</difficult>
    <bndbox>
      <xmin>282</xmin>
      <ymin>637</ymin>
      <xmax>605</xmax>
      <ymax>662</ymax>
    </bndbox>
    <index>5</index>
    <review_code>C_v001</review_code>
  </object>
  <object>
    <name>Vehicle_Bus</name>
    <pose>Unspecified</pose>
    <truncated>0</truncated>
    <difficult>0</difficult>
    <bndbox>
      <xmin>599</xmin>
      <ymin>324</ymin>
      <xmax>1919</xmax>
      <ymax>812</ymax>
    </bndbox>
    <index>7</index>
    <review_code>C_v001</review_code>
  </object>
  <object>
    <name>TrafficSign_Speed</name>
    <pose>Unspecified</pose>
    <truncated>0</truncated>
    <difficult>0</difficult>
    <bndbox>
      <xmin>1046</xmin>
      <ymin>166</ymin>
      <xmax>1114</xmax>
      <ymax>235</ymax>
    </bndbox>
    <index>8</index>
    <review_code>C_v001</review_code>
  </object>
  <object>
    <name>TrafficLight_Red</name>
    <pose>Unspecified</pose>
    <truncated>0</truncated>
    <difficult>0</difficult>
    <bndbox>
      <xmin>808</xmin>
      <ymin>211</ymin>
      <xmax>920</xmax>
      <ymax>242</ymax>
    </bndbox>
    <index>9</index>
    <review_code>C_v001</review_code>
  </object>
  <object>
    <name>Vehicle_Car</name>
    <pose>Unspecified</pose>
    <truncated>0</truncated>
    <difficult>0</difficult>
    <bndbox>
      <xmin>502</xmin>
      <ymin>533</ymin>
      <xmax>557</xmax>
      <ymax>563</ymax>
    </bndbox>
    <index>10</index>
    <review_code>C_v001</review_code>
  </object>
  <object>
    <name>Vehicle_Car</name>
    <pose>Unspecified</pose>
    <truncated>0</truncated>
    <difficult>0</difficult>
    <bndbox>
      <xmin>507</xmin>
      <ymin>552</ymin>
      <xmax>572</xmax>
      <ymax>602</ymax>
    </bndbox>
    <index>11</index>
    <review_code>C_v001</review_code>
  </object>
  <object>
    <name>Vehicle_Car</name>
    <pose>Unspecified</pose>
    <truncated>0</truncated>
    <difficult>0</difficult>
    <bndbox>
      <xmin>477</xmin>
      <ymin>556</ymin>
      <xmax>518</xmax>
      <ymax>612</ymax>
    </bndbox>
    <index>12</index>
    <review_code>C_v001</review_code>
  </object>
  <object>
    <name>Vehicle_Car</name>
    <pose>Unspecified</pose>
    <truncated>0</truncated>
    <difficult>0</difficult>
    <bndbox>
      <xmin>466</xmin>
      <ymin>556</ymin>
      <xmax>493</xmax>
      <ymax>614</ymax>
    </bndbox>
    <index>13</index>
    <review_code>C_v001</review_code>
  </object>
  <object>
    <name>Vehicle_Unknown</name>
    <pose>Unspecified</pose>
    <truncated>0</truncated>
    <difficult>0</difficult>
    <bndbox>
      <xmin>335</xmin>
      <ymin>528</ymin>
      <xmax>421</xmax>
      <ymax>558</ymax>
    </bndbox>
    <index>14</index>
    <review_code>C_v001</review_code>
  </object>
  <object>
    <name>Vehicle_Car</name>
    <pose>Unspecified</pose>
    <truncated>0</truncated>
    <difficult>0</difficult>
    <bndbox>
      <xmin>350</xmin>
      <ymin>540</ymin>
      <xmax>485</xmax>
      <ymax>642</ymax>
    </bndbox>
    <index>15</index>
    <review_code>C_v001</review_code>
  </object>
  <object>
    <name>Vehicle_Car</name>
    <pose>Unspecified</pose>
    <truncated>0</truncated>
    <difficult>0</difficult>
    <bndbox>
      <xmin>274</xmin>
      <ymin>545</ymin>
      <xmax>372</xmax>
      <ymax>637</ymax>
    </bndbox>
    <index>16</index>
    <review_code>C_v001</review_code>
  </object>
  <object>
    <name>Vehicle_Car</name>
    <pose>Unspecified</pose>
    <truncated>0</truncated>
    <difficult>0</difficult>
    <bndbox>
      <xmin>267</xmin>
      <ymin>565</ymin>
      <xmax>295</xmax>
      <ymax>642</ymax>
    </bndbox>
    <index>17</index>
    <review_code>C_v001</review_code>
  </object>
  <object>
    <name>Vehicle_Bus</name>
    <pose>Unspecified</pose>
    <truncated>0</truncated>
    <difficult>0</difficult>
    <bndbox>
      <xmin>0</xmin>
      <ymin>348</ymin>
      <xmax>282</xmax>
      <ymax>775</ymax>
    </bndbox>
    <index>18</index>
    <review_code>C_v001</review_code>
  </object>
  <object>
    <name>TrafficSign_Else</name>
    <pose>Unspecified</pose>
    <truncated>0</truncated>
    <difficult>0</difficult>
    <bndbox>
      <xmin>1481</xmin>
      <ymin>340</ymin>
      <xmax>1517</xmax>
      <ymax>421</ymax>
    </bndbox>
    <index>19</index>
    <review_code>C_v001</review_code>
  </object>
  <object>
    <name>RoadMarkArrow_Else</name>
    <pose>Unspecified</pose>
    <truncated>0</truncated>
    <difficult>0</difficult>
    <bndbox>
      <xmin>559</xmin>
      <ymin>621</ymin>
      <xmax>601</xmax>
      <ymax>633</ymax>
    </bndbox>
    <index>20</index>
    <review_code>C_v001</review_code>
  </object>
</annotation>
