<?xml version="1.0" encoding="UTF-8"?>
<annotation>
  <ver>v001_1</ver>
  <folder>1</folder>
  <filename>1_20200731_071547_001590.jpg</filename>
  <path>C:\Users\A\Desktop\검수\20200731_원주_손지영\20200731_원주_손지영\20200731_071547\1\</path>
  <source>
    <database>KATECH_DB</database>
  </source>
  <size>
    <width>1920</width>
    <height>1080</height>
    <depth>3</depth>
  </size>
  <segmented>0</segmented>
  <index_max>14</index_max>
  <object>
    <name>TrafficSign_Else</name>
    <pose>Unspecified</pose>
    <truncated>0</truncated>
    <difficult>0</difficult>
    <bndbox>
      <xmin>1675</xmin>
      <ymin>265</ymin>
      <xmax>1740</xmax>
      <ymax>328</ymax>
    </bndbox>
    <index>5</index>
    <review_code>C_v001</review_code>
  </object>
  <object>
    <name>TrafficSign_Else</name>
    <pose>Unspecified</pose>
    <truncated>0</truncated>
    <difficult>0</difficult>
    <bndbox>
      <xmin>1490</xmin>
      <ymin>238</ymin>
      <xmax>1532</xmax>
      <ymax>280</ymax>
    </bndbox>
    <index>6</index>
    <review_code>C_v001</review_code>
  </object>
  <object>
    <name>TrafficLight_Green</name>
    <pose>Unspecified</pose>
    <truncated>0</truncated>
    <difficult>0</difficult>
    <bndbox>
      <xmin>1555</xmin>
      <ymin>259</ymin>
      <xmax>1606</xmax>
      <ymax>278</ymax>
    </bndbox>
    <index>7</index>
    <review_code>C_v001</review_code>
  </object>
  <object>
    <name>TrafficLight_Green</name>
    <pose>Unspecified</pose>
    <truncated>0</truncated>
    <difficult>0</difficult>
    <bndbox>
      <xmin>1411</xmin>
      <ymin>268</ymin>
      <xmax>1464</xmax>
      <ymax>287</ymax>
    </bndbox>
    <index>8</index>
    <review_code>C_v001</review_code>
  </object>
  <object>
    <name>RoadMark_Character</name>
    <pose>Unspecified</pose>
    <truncated>0</truncated>
    <difficult>0</difficult>
    <bndbox>
      <xmin>885</xmin>
      <ymin>588</ymin>
      <xmax>957</xmax>
      <ymax>595</ymax>
    </bndbox>
    <index>9</index>
    <review_code>C_v001</review_code>
  </object>
  <object>
    <name>RoadMark_Character</name>
    <pose>Unspecified</pose>
    <truncated>0</truncated>
    <difficult>0</difficult>
    <bndbox>
      <xmin>775</xmin>
      <ymin>595</ymin>
      <xmax>957</xmax>
      <ymax>605</ymax>
    </bndbox>
    <index>10</index>
    <review_code>C_v001</review_code>
  </object>
  <object>
    <name>RoadMark_StopLine</name>
    <pose>Unspecified</pose>
    <truncated>0</truncated>
    <difficult>0</difficult>
    <bndbox>
      <xmin>929</xmin>
      <ymin>571</ymin>
      <xmax>1381</xmax>
      <ymax>574</ymax>
    </bndbox>
    <index>11</index>
    <review_code>C_v001</review_code>
  </object>
  <object>
    <name>Vehicle_Car</name>
    <pose>Unspecified</pose>
    <truncated>0</truncated>
    <difficult>0</difficult>
    <bndbox>
      <xmin>1588</xmin>
      <ymin>387</ymin>
      <xmax>1919</xmax>
      <ymax>891</ymax>
    </bndbox>
    <index>12</index>
    <review_code>C_v001</review_code>
  </object>
  <object>
    <name>Vehicle_Car</name>
    <pose>Unspecified</pose>
    <truncated>0</truncated>
    <difficult>0</difficult>
    <bndbox>
      <xmin>1362</xmin>
      <ymin>455</ymin>
      <xmax>1651</xmax>
      <ymax>692</ymax>
    </bndbox>
    <index>13</index>
    <review_code>C_v001</review_code>
  </object>
  <object>
    <name>Vehicle_Car</name>
    <pose>Unspecified</pose>
    <truncated>0</truncated>
    <difficult>0</difficult>
    <bndbox>
      <xmin>1379</xmin>
      <ymin>440</ymin>
      <xmax>1554</xmax>
      <ymax>525</ymax>
    </bndbox>
    <index>14</index>
    <review_code>C_v001</review_code>
  </object>
  <object>
    <name>Vehicle_Car</name>
    <pose>Unspecified</pose>
    <truncated>0</truncated>
    <difficult>0</difficult>
    <bndbox>
      <xmin>1304</xmin>
      <ymin>472</ymin>
      <xmax>1399</xmax>
      <ymax>534</ymax>
    </bndbox>
    <index>15</index>
    <review_code>C_v001</review_code>
  </object>
  <object>
    <name>Vehicle_Unknown</name>
    <pose>Unspecified</pose>
    <truncated>0</truncated>
    <difficult>0</difficult>
    <bndbox>
      <xmin>919</xmin>
      <ymin>136</ymin>
      <xmax>1281</xmax>
      <ymax>629</ymax>
    </bndbox>
    <index>16</index>
    <review_code>C_v001</review_code>
  </object>
  <object>
    <name>Vehicle_Car</name>
    <pose>Unspecified</pose>
    <truncated>0</truncated>
    <difficult>0</difficult>
    <bndbox>
      <xmin>36</xmin>
      <ymin>471</ymin>
      <xmax>556</xmax>
      <ymax>800</ymax>
    </bndbox>
    <index>17</index>
    <review_code>C_v001</review_code>
  </object>
  <object>
    <name>Vehicle_Bus</name>
    <pose>Unspecified</pose>
    <truncated>0</truncated>
    <difficult>0</difficult>
    <bndbox>
      <xmin>1630</xmin>
      <ymin>404</ymin>
      <xmax>1680</xmax>
      <ymax>450</ymax>
    </bndbox>
    <index>18</index>
    <review_code>C_v001</review_code>
  </object>
</annotation>
