<?xml version="1.0" encoding="UTF-8"?>
<annotation>
  <ver>v001_1</ver>
  <folder>1</folder>
  <filename>1_20211007_220940_004350.png</filename>
  <path>F:\GT\검수작업\D\1\</path>
  <source>
    <database>KATECH_DB</database>
  </source>
  <size>
    <width>1920</width>
    <height>1080</height>
    <depth>3</depth>
  </size>
  <segmented>0</segmented>
  <index_max>12</index_max>
  <object>
    <name>Vehicle_Unknown</name>
    <pose>Unspecified</pose>
    <truncated>0</truncated>
    <difficult>0</difficult>
    <bndbox>
      <xmin>1436</xmin>
      <ymin>428</ymin>
      <xmax>1790</xmax>
      <ymax>694</ymax>
    </bndbox>
    <index>1</index>
    <review_code>C_v001</review_code>
  </object>
  <object>
    <name>Vehicle_Car</name>
    <pose>Unspecified</pose>
    <truncated>0</truncated>
    <difficult>0</difficult>
    <bndbox>
      <xmin>1736</xmin>
      <ymin>428</ymin>
      <xmax>1894</xmax>
      <ymax>609</ymax>
    </bndbox>
    <index>2</index>
    <review_code>C_v001</review_code>
  </object>
  <object>
    <name>TrafficSign_Else</name>
    <pose>Unspecified</pose>
    <truncated>0</truncated>
    <difficult>0</difficult>
    <bndbox>
      <xmin>953</xmin>
      <ymin>538</ymin>
      <xmax>1014</xmax>
      <ymax>600</ymax>
    </bndbox>
    <index>3</index>
    <review_code>C_v001</review_code>
  </object>
  <object>
    <name>RoadMark_Character</name>
    <pose>Unspecified</pose>
    <truncated>0</truncated>
    <difficult>0</difficult>
    <bndbox>
      <xmin>719</xmin>
      <ymin>834</ymin>
      <xmax>1383</xmax>
      <ymax>918</ymax>
    </bndbox>
    <index>5</index>
    <review_code>C_v001</review_code>
  </object>
  <object>
    <name>RoadMark_Number</name>
    <pose>Unspecified</pose>
    <truncated>0</truncated>
    <difficult>0</difficult>
    <bndbox>
      <xmin>0</xmin>
      <ymin>852</ymin>
      <xmax>405</xmax>
      <ymax>926</ymax>
    </bndbox>
    <index>6</index>
    <review_code>C_v001</review_code>
  </object>
  <object>
    <name>RoadMark_StopLine</name>
    <pose>Unspecified</pose>
    <truncated>0</truncated>
    <difficult>0</difficult>
    <bndbox>
      <xmin>656</xmin>
      <ymin>814</ymin>
      <xmax>1919</xmax>
      <ymax>833</ymax>
    </bndbox>
    <index>7</index>
    <review_code>C_v001</review_code>
  </object>
  <object>
    <name>RoadMark_Crosswalk</name>
    <pose>Unspecified</pose>
    <truncated>0</truncated>
    <difficult>0</difficult>
    <bndbox>
      <xmin>0</xmin>
      <ymin>716</ymin>
      <xmax>1869</xmax>
      <ymax>807</ymax>
    </bndbox>
    <index>8</index>
    <review_code>C_v001</review_code>
  </object>
  <line>
    <name>Lane_White_Dash</name>
    <pose>Unspecified</pose>
    <truncated>0</truncated>
    <difficult>0</difficult>
    <controlPt>
      <x>1359</x>
      <y>830</y>
      <x>1575</x>
      <y>987</y>
      <x>1706</x>
      <y>1078</y>
    </controlPt>
    <index>9</index>
    <review_code>C_v001</review_code>
  </line>
  <line>
    <name>Lane_Yellow_Solid</name>
    <pose>Unspecified</pose>
    <truncated>0</truncated>
    <difficult>0</difficult>
    <controlPt>
      <x>692</x>
      <y>793</y>
      <x>449</x>
      <y>1079</y>
    </controlPt>
    <index>10</index>
    <review_code>C_v001</review_code>
  </line>
  <line>
    <name>Lane_Yellow_Solid</name>
    <pose>Unspecified</pose>
    <truncated>0</truncated>
    <difficult>0</difficult>
    <controlPt>
      <x>635</x>
      <y>791</y>
      <x>583</x>
      <y>841</y>
      <x>323</x>
      <y>1079</y>
    </controlPt>
    <index>11</index>
    <review_code>C_v001</review_code>
  </line>
  <object>
    <name>Vehicle_Car</name>
    <pose>Unspecified</pose>
    <truncated>0</truncated>
    <difficult>0</difficult>
    <bndbox>
      <xmin>0</xmin>
      <ymin>595</ymin>
      <xmax>26</xmax>
      <ymax>747</ymax>
    </bndbox>
    <index>12</index>
    <review_code>C_v001</review_code>
  </object>
</annotation>