<?xml version="1.0" encoding="UTF-8"?>
<annotation>
  <ver>v001_1</ver>
  <folder>2</folder>
  <filename>2_20200709_172541_001650.jpg</filename>
  <path>E:\1000.김민서\1.알바\1.검수 프로그램\2.검수용 자료\5.201013_서울1차_김민서(수정)\5.김혜랑\20200709_172541\2\</path>
  <source>
    <database>KATECH_DB</database>
  </source>
  <size>
    <width>1920</width>
    <height>1080</height>
    <depth>3</depth>
  </size>
  <segmented>0</segmented>
  <index_max>4</index_max>
  <object>
    <name>Vehicle_Car</name>
    <pose>Unspecified</pose>
    <truncated>0</truncated>
    <difficult>0</difficult>
    <bndbox>
      <xmin>0</xmin>
      <ymin>553</ymin>
      <xmax>156</xmax>
      <ymax>599</ymax>
    </bndbox>
    <index>5</index>
    <review_code>C_v001</review_code>
  </object>
  <object>
    <name>Vehicle_Car</name>
    <pose>Unspecified</pose>
    <truncated>0</truncated>
    <difficult>0</difficult>
    <bndbox>
      <xmin>99</xmin>
      <ymin>529</ymin>
      <xmax>386</xmax>
      <ymax>629</ymax>
    </bndbox>
    <index>6</index>
    <review_code>C_v001</review_code>
  </object>
  <object>
    <name>Vehicle_Car</name>
    <pose>Unspecified</pose>
    <truncated>0</truncated>
    <difficult>0</difficult>
    <bndbox>
      <xmin>1126</xmin>
      <ymin>526</ymin>
      <xmax>1299</xmax>
      <ymax>631</ymax>
    </bndbox>
    <index>7</index>
    <review_code>C_v001</review_code>
  </object>
  <object>
    <name>TrafficSign_Else</name>
    <pose>Unspecified</pose>
    <truncated>0</truncated>
    <difficult>0</difficult>
    <bndbox>
      <xmin>932</xmin>
      <ymin>360</ymin>
      <xmax>962</xmax>
      <ymax>389</ymax>
    </bndbox>
    <index>8</index>
    <review_code>C_v001</review_code>
  </object>
</annotation>
