<?xml version="1.0" encoding="UTF-8"?>
<annotation>
  <ver>v001_1</ver>
  <folder>3</folder>
  <filename>3_20200708_122437_005100.jpg</filename>
  <path>D:\한자연\검수4차(세종2차)_20201030\8.강인선-20201029T182414Z-001\8.강인선\작업자1.김정희\2차수 20201029\20200708_122437\3\</path>
  <source>
    <database>KATECH_DB</database>
  </source>
  <size>
    <width>1920</width>
    <height>1080</height>
    <depth>3</depth>
  </size>
  <segmented>0</segmented>
  <index_max>9</index_max>
  <object>
    <name>Vehicle_Car</name>
    <pose>Unspecified</pose>
    <truncated>0</truncated>
    <difficult>0</difficult>
    <bndbox>
      <xmin>1518</xmin>
      <ymin>518</ymin>
      <xmax>1642</xmax>
      <ymax>601</ymax>
    </bndbox>
    <index>3</index>
    <review_code>C_v001</review_code>
  </object>
  <object>
    <name>Vehicle_Unknown</name>
    <pose>Unspecified</pose>
    <truncated>0</truncated>
    <difficult>0</difficult>
    <bndbox>
      <xmin>1411</xmin>
      <ymin>514</ymin>
      <xmax>1574</xmax>
      <ymax>558</ymax>
    </bndbox>
    <index>4</index>
    <review_code>C_v001</review_code>
  </object>
  <object>
    <name>Vehicle_Car</name>
    <pose>Unspecified</pose>
    <truncated>0</truncated>
    <difficult>0</difficult>
    <bndbox>
      <xmin>1299</xmin>
      <ymin>534</ymin>
      <xmax>1354</xmax>
      <ymax>576</ymax>
    </bndbox>
    <index>6</index>
    <review_code>C_v001</review_code>
  </object>
  <object>
    <name>Vehicle_Unknown</name>
    <pose>Unspecified</pose>
    <truncated>0</truncated>
    <difficult>0</difficult>
    <bndbox>
      <xmin>1285</xmin>
      <ymin>532</ymin>
      <xmax>1378</xmax>
      <ymax>557</ymax>
    </bndbox>
    <index>7</index>
    <review_code>C_v001</review_code>
  </object>
  <object>
    <name>Vehicle_Unknown</name>
    <pose>Unspecified</pose>
    <truncated>0</truncated>
    <difficult>0</difficult>
    <bndbox>
      <xmin>955</xmin>
      <ymin>362</ymin>
      <xmax>1148</xmax>
      <ymax>408</ymax>
    </bndbox>
    <index>8</index>
    <review_code>C_v001</review_code>
  </object>
  <object>
    <name>Vehicle_Car</name>
    <pose>Unspecified</pose>
    <truncated>0</truncated>
    <difficult>0</difficult>
    <bndbox>
      <xmin>706</xmin>
      <ymin>403</ymin>
      <xmax>1303</xmax>
      <ymax>936</ymax>
    </bndbox>
    <index>9</index>
    <review_code>C_v001</review_code>
  </object>
  <object>
    <name>Vehicle_Car</name>
    <pose>Unspecified</pose>
    <truncated>0</truncated>
    <difficult>0</difficult>
    <bndbox>
      <xmin>559</xmin>
      <ymin>512</ymin>
      <xmax>759</xmax>
      <ymax>698</ymax>
    </bndbox>
    <index>10</index>
    <review_code>C_v001</review_code>
  </object>
  <object>
    <name>Vehicle_Car</name>
    <pose>Unspecified</pose>
    <truncated>0</truncated>
    <difficult>0</difficult>
    <bndbox>
      <xmin>53</xmin>
      <ymin>485</ymin>
      <xmax>581</xmax>
      <ymax>786</ymax>
    </bndbox>
    <index>11</index>
    <review_code>C_v001</review_code>
  </object>
  <object>
    <name>Vehicle_Car</name>
    <pose>Unspecified</pose>
    <truncated>0</truncated>
    <difficult>0</difficult>
    <bndbox>
      <xmin>0</xmin>
      <ymin>570</ymin>
      <xmax>308</xmax>
      <ymax>984</ymax>
    </bndbox>
    <index>12</index>
    <review_code>C_v001</review_code>
  </object>
</annotation>
