<?xml version="1.0" encoding="UTF-8"?>
<annotation>
  <ver>v001_1</ver>
  <folder>3</folder>
  <filename>3_20200708_115938_007410.jpg</filename>
  <path>I:\수원2_심혜림_검수작업\7차_서지선_세종4차수\작업자2.오지영-20201110T151055Z-001\작업자2.오지영\4차수 20201110\20200708_115938\3\</path>
  <source>
    <database>KATECH_DB</database>
  </source>
  <size>
    <width>1920</width>
    <height>1080</height>
    <depth>3</depth>
  </size>
  <segmented>0</segmented>
  <index_max>15</index_max>
  <object>
    <name>Vehicle_Bus</name>
    <pose>Unspecified</pose>
    <truncated>0</truncated>
    <difficult>0</difficult>
    <bndbox>
      <xmin>0</xmin>
      <ymin>0</ymin>
      <xmax>153</xmax>
      <ymax>913</ymax>
    </bndbox>
    <index>1</index>
    <review_code>C_v001</review_code>
  </object>
  <object>
    <name>Vehicle_Unknown</name>
    <pose>Unspecified</pose>
    <truncated>0</truncated>
    <difficult>0</difficult>
    <bndbox>
      <xmin>341</xmin>
      <ymin>494</ymin>
      <xmax>478</xmax>
      <ymax>540</ymax>
    </bndbox>
    <index>2</index>
    <review_code>C_v001</review_code>
  </object>
  <object>
    <name>Vehicle_Car</name>
    <pose>Unspecified</pose>
    <truncated>0</truncated>
    <difficult>0</difficult>
    <bndbox>
      <xmin>463</xmin>
      <ymin>529</ymin>
      <xmax>613</xmax>
      <ymax>621</ymax>
    </bndbox>
    <index>3</index>
    <review_code>C_v001</review_code>
  </object>
  <object>
    <name>Vehicle_Car</name>
    <pose>Unspecified</pose>
    <truncated>0</truncated>
    <difficult>0</difficult>
    <bndbox>
      <xmin>682</xmin>
      <ymin>536</ymin>
      <xmax>752</xmax>
      <ymax>586</ymax>
    </bndbox>
    <index>4</index>
    <review_code>C_v001</review_code>
  </object>
  <object>
    <name>Vehicle_Bus</name>
    <pose>Unspecified</pose>
    <truncated>0</truncated>
    <difficult>0</difficult>
    <bndbox>
      <xmin>748</xmin>
      <ymin>461</ymin>
      <xmax>874</xmax>
      <ymax>592</ymax>
    </bndbox>
    <index>5</index>
    <review_code>C_v001</review_code>
  </object>
  <object>
    <name>Vehicle_Car</name>
    <pose>Unspecified</pose>
    <truncated>0</truncated>
    <difficult>0</difficult>
    <bndbox>
      <xmin>871</xmin>
      <ymin>520</ymin>
      <xmax>1000</xmax>
      <ymax>633</ymax>
    </bndbox>
    <index>6</index>
    <review_code>C_v001</review_code>
  </object>
  <object>
    <name>Vehicle_Unknown</name>
    <pose>Unspecified</pose>
    <truncated>0</truncated>
    <difficult>0</difficult>
    <bndbox>
      <xmin>1020</xmin>
      <ymin>432</ymin>
      <xmax>1173</xmax>
      <ymax>607</ymax>
    </bndbox>
    <index>7</index>
    <review_code>C_v001</review_code>
  </object>
  <object>
    <name>Vehicle_Unknown</name>
    <pose>Unspecified</pose>
    <truncated>0</truncated>
    <difficult>0</difficult>
    <bndbox>
      <xmin>1309</xmin>
      <ymin>496</ymin>
      <xmax>1399</xmax>
      <ymax>547</ymax>
    </bndbox>
    <index>8</index>
    <review_code>C_v001</review_code>
  </object>
  <object>
    <name>TrafficSign_Else</name>
    <pose>Unspecified</pose>
    <truncated>0</truncated>
    <difficult>0</difficult>
    <bndbox>
      <xmin>1371</xmin>
      <ymin>455</ymin>
      <xmax>1411</xmax>
      <ymax>503</ymax>
    </bndbox>
    <index>9</index>
    <review_code>C_v001</review_code>
  </object>
  <object>
    <name>Vehicle_Car</name>
    <pose>Unspecified</pose>
    <truncated>0</truncated>
    <difficult>0</difficult>
    <bndbox>
      <xmin>1373</xmin>
      <ymin>524</ymin>
      <xmax>1437</xmax>
      <ymax>549</ymax>
    </bndbox>
    <index>10</index>
    <review_code>C_v001</review_code>
  </object>
  <object>
    <name>Vehicle_Car</name>
    <pose>Unspecified</pose>
    <truncated>0</truncated>
    <difficult>0</difficult>
    <bndbox>
      <xmin>1428</xmin>
      <ymin>528</ymin>
      <xmax>1520</xmax>
      <ymax>568</ymax>
    </bndbox>
    <index>11</index>
    <review_code>C_v001</review_code>
  </object>
  <object>
    <name>Vehicle_Car</name>
    <pose>Unspecified</pose>
    <truncated>0</truncated>
    <difficult>0</difficult>
    <bndbox>
      <xmin>1510</xmin>
      <ymin>539</ymin>
      <xmax>1595</xmax>
      <ymax>600</ymax>
    </bndbox>
    <index>12</index>
    <review_code>C_v001</review_code>
  </object>
  <object>
    <name>Vehicle_Car</name>
    <pose>Unspecified</pose>
    <truncated>0</truncated>
    <difficult>0</difficult>
    <bndbox>
      <xmin>1579</xmin>
      <ymin>533</ymin>
      <xmax>1681</xmax>
      <ymax>608</ymax>
    </bndbox>
    <index>13</index>
    <review_code>C_v001</review_code>
  </object>
  <object>
    <name>Vehicle_Car</name>
    <pose>Unspecified</pose>
    <truncated>0</truncated>
    <difficult>0</difficult>
    <bndbox>
      <xmin>1701</xmin>
      <ymin>521</ymin>
      <xmax>1886</xmax>
      <ymax>620</ymax>
    </bndbox>
    <index>14</index>
    <review_code>C_v001</review_code>
  </object>
  <object>
    <name>Vehicle_Car</name>
    <pose>Unspecified</pose>
    <truncated>0</truncated>
    <difficult>0</difficult>
    <bndbox>
      <xmin>1854</xmin>
      <ymin>525</ymin>
      <xmax>1919</xmax>
      <ymax>630</ymax>
    </bndbox>
    <index>15</index>
    <review_code>C_v001</review_code>
  </object>
</annotation>
