<?xml version="1.0" encoding="UTF-8"?>
<annotation>
  <ver>v001_1</ver>
  <folder>1</folder>
  <filename>3_20211007_205231_000300.png</filename>
  <path>C:\Users\KATECH-02\Desktop\E\1\</path>
  <source>
    <database>KATECH_DB</database>
  </source>
  <size>
    <width>1920</width>
    <height>1080</height>
    <depth>3</depth>
  </size>
  <segmented>0</segmented>
  <index_max>15</index_max>
  <line>
    <name>Lane_Yellow_Solid</name>
    <pose>Unspecified</pose>
    <truncated>0</truncated>
    <difficult>0</difficult>
    <controlPt>
      <x>809</x>
      <y>595</y>
      <x>726</x>
      <y>620</y>
      <x>411</x>
      <y>708</y>
    </controlPt>
    <index>1</index>
    <review_code>C_v001</review_code>
  </line>
  <line>
    <name>Lane_Yellow_Solid</name>
    <pose>Unspecified</pose>
    <truncated>0</truncated>
    <difficult>0</difficult>
    <controlPt>
      <x>812</x>
      <y>599</y>
      <x>694</x>
      <y>637</y>
      <x>416</x>
      <y>725</y>
    </controlPt>
    <index>2</index>
    <review_code>C_v001</review_code>
  </line>
  <line>
    <name>Lane_White_Dash</name>
    <pose>Unspecified</pose>
    <truncated>0</truncated>
    <difficult>0</difficult>
    <controlPt>
      <x>898</x>
      <y>598</y>
      <x>853</x>
      <y>647</y>
      <x>756</x>
      <y>735</y>
      <x>698</x>
      <y>785</y>
    </controlPt>
    <index>3</index>
    <review_code>C_v001</review_code>
  </line>
  <line>
    <name>Lane_White_Dash</name>
    <pose>Unspecified</pose>
    <truncated>0</truncated>
    <difficult>0</difficult>
    <controlPt>
      <x>992</x>
      <y>598</y>
      <x>1033</x>
      <y>628</y>
      <x>1054</x>
      <y>645</y>
      <x>1095</x>
      <y>680</y>
      <x>1142</x>
      <y>729</y>
      <x>1168</x>
      <y>752</y>
      <x>1205</x>
      <y>787</y>
    </controlPt>
    <index>4</index>
    <review_code>C_v001</review_code>
  </line>
  <line>
    <name>Lane_Yellow_Solid</name>
    <pose>Unspecified</pose>
    <truncated>0</truncated>
    <difficult>0</difficult>
    <controlPt>
      <x>1072</x>
      <y>593</y>
      <x>1147</x>
      <y>614</y>
      <x>1186</x>
      <y>624</y>
      <x>1241</x>
      <y>639</y>
      <x>1374</x>
      <y>679</y>
      <x>1523</x>
      <y>722</y>
      <x>1614</x>
      <y>751</y>
    </controlPt>
    <index>5</index>
    <review_code>C_v001</review_code>
  </line>
  <object>
    <name>Vehicle_Bus</name>
    <pose>Unspecified</pose>
    <truncated>0</truncated>
    <difficult>0</difficult>
    <bndbox>
      <xmin>0</xmin>
      <ymin>159</ymin>
      <xmax>520</xmax>
      <ymax>745</ymax>
    </bndbox>
    <index>7</index>
    <review_code>C_v001</review_code>
  </object>
  <object>
    <name>Vehicle_Car</name>
    <pose>Unspecified</pose>
    <truncated>0</truncated>
    <difficult>0</difficult>
    <bndbox>
      <xmin>769</xmin>
      <ymin>553</ymin>
      <xmax>824</xmax>
      <ymax>590</ymax>
    </bndbox>
    <index>8</index>
    <review_code>C_v001</review_code>
  </object>
  <object>
    <name>Vehicle_Bus</name>
    <pose>Unspecified</pose>
    <truncated>0</truncated>
    <difficult>0</difficult>
    <bndbox>
      <xmin>959</xmin>
      <ymin>525</ymin>
      <xmax>1004</xmax>
      <ymax>582</ymax>
    </bndbox>
    <index>9</index>
    <review_code>C_v001</review_code>
  </object>
  <object>
    <name>RoadMark_StopLine</name>
    <pose>Unspecified</pose>
    <truncated>0</truncated>
    <difficult>0</difficult>
    <bndbox>
      <xmin>818</xmin>
      <ymin>594</ymin>
      <xmax>1083</xmax>
      <ymax>598</ymax>
    </bndbox>
    <index>10</index>
    <review_code>C_v001</review_code>
  </object>
  <object>
    <name>RoadMarkArrow_Left</name>
    <pose>Unspecified</pose>
    <truncated>0</truncated>
    <difficult>0</difficult>
    <bndbox>
      <xmin>821</xmin>
      <ymin>600</ymin>
      <xmax>853</xmax>
      <ymax>612</ymax>
    </bndbox>
    <index>11</index>
    <review_code>C_v001</review_code>
  </object>
  <object>
    <name>RoadMarkArrow_Straight</name>
    <pose>Unspecified</pose>
    <truncated>0</truncated>
    <difficult>0</difficult>
    <bndbox>
      <xmin>932</xmin>
      <ymin>600</ymin>
      <xmax>956</xmax>
      <ymax>612</ymax>
    </bndbox>
    <index>12</index>
    <review_code>C_v001</review_code>
  </object>
  <object>
    <name>RoadMarkArrow_StraightRight</name>
    <pose>Unspecified</pose>
    <truncated>0</truncated>
    <difficult>0</difficult>
    <bndbox>
      <xmin>1046</xmin>
      <ymin>599</ymin>
      <xmax>1096</xmax>
      <ymax>611</ymax>
    </bndbox>
    <index>13</index>
    <review_code>C_v001</review_code>
  </object>
  <object>
    <name>TrafficLight_Green</name>
    <pose>Unspecified</pose>
    <truncated>0</truncated>
    <difficult>0</difficult>
    <bndbox>
      <xmin>954</xmin>
      <ymin>412</ymin>
      <xmax>997</xmax>
      <ymax>423</ymax>
    </bndbox>
    <index>14</index>
    <review_code>C_v001</review_code>
  </object>
  <object>
    <name>TrafficLight_Green</name>
    <pose>Unspecified</pose>
    <truncated>0</truncated>
    <difficult>0</difficult>
    <bndbox>
      <xmin>946</xmin>
      <ymin>477</ymin>
      <xmax>972</xmax>
      <ymax>486</ymax>
    </bndbox>
    <index>15</index>
    <review_code>C_v001</review_code>
  </object>
</annotation>