<annotation>
  <object>
    <name>Vehicle</name>
    <bndbox>
      <xmin>1318</xmin>
      <ymin>412</ymin>
      <xmax>1357</xmax>
      <ymax>431</ymax>
    </bndbox>
    <confidence>0.255377</confidence>
  </object>
  <object>
    <name>Vehicle</name>
    <bndbox>
      <xmin>845</xmin>
      <ymin>459</ymin>
      <xmax>884</xmax>
      <ymax>483</ymax>
    </bndbox>
    <confidence>0.660866</confidence>
  </object>
  <object>
    <name>Vehicle</name>
    <bndbox>
      <xmin>1098</xmin>
      <ymin>459</ymin>
      <xmax>1128</xmax>
      <ymax>481</ymax>
    </bndbox>
    <confidence>0.779299</confidence>
  </object>
  <object>
    <name>Vehicle</name>
    <bndbox>
      <xmin>1040</xmin>
      <ymin>461</ymin>
      <xmax>1076</xmax>
      <ymax>496</ymax>
    </bndbox>
    <confidence>0.886947</confidence>
  </object>
  <object>
    <name>Vehicle</name>
    <bndbox>
      <xmin>970</xmin>
      <ymin>472</ymin>
      <xmax>1004</xmax>
      <ymax>501</ymax>
    </bndbox>
    <confidence>0.895668</confidence>
  </object>
  <object>
    <name>Vehicle</name>
    <bndbox>
      <xmin>497</xmin>
      <ymin>424</ymin>
      <xmax>645</xmax>
      <ymax>502</ymax>
    </bndbox>
    <confidence>0.909441</confidence>
  </object>
  <object>
    <name>Vehicle</name>
    <bndbox>
      <xmin>928</xmin>
      <ymin>470</ymin>
      <xmax>981</xmax>
      <ymax>515</ymax>
    </bndbox>
    <confidence>0.936483</confidence>
  </object>
</annotation>
