<annotation>
  <object>
    <name>TrafficSign</name>
    <bndbox>
      <xmin>862</xmin>
      <ymin>270</ymin>
      <xmax>894</xmax>
      <ymax>318</ymax>
    </bndbox>
    <confidence>0.272948</confidence>
  </object>
  <object>
    <name>TrafficLight</name>
    <bndbox>
      <xmin>585</xmin>
      <ymin>462</ymin>
      <xmax>607</xmax>
      <ymax>468</ymax>
    </bndbox>
    <confidence>0.433258</confidence>
  </object>
  <object>
    <name>Vehicle</name>
    <bndbox>
      <xmin>300</xmin>
      <ymin>511</ymin>
      <xmax>331</xmax>
      <ymax>546</ymax>
    </bndbox>
    <confidence>0.763375</confidence>
  </object>
  <object>
    <name>TrafficSign</name>
    <bndbox>
      <xmin>860</xmin>
      <ymin>268</ymin>
      <xmax>996</xmax>
      <ymax>319</ymax>
    </bndbox>
    <confidence>0.800704</confidence>
  </object>
  <object>
    <name>Vehicle</name>
    <bndbox>
      <xmin>830</xmin>
      <ymin>427</ymin>
      <xmax>1041</xmax>
      <ymax>638</ymax>
    </bndbox>
    <confidence>0.964075</confidence>
  </object>
  <object>
    <name>Vehicle</name>
    <bndbox>
      <xmin>1128</xmin>
      <ymin>397</ymin>
      <xmax>1374</xmax>
      <ymax>574</ymax>
    </bndbox>
    <confidence>0.964661</confidence>
  </object>
</annotation>
