<annotation>
  <object>
    <name>TrafficLight</name>
    <bndbox>
      <xmin>1010</xmin>
      <ymin>465</ymin>
      <xmax>1024</xmax>
      <ymax>470</ymax>
    </bndbox>
    <confidence>0.274357</confidence>
  </object>
  <object>
    <name>Vehicle</name>
    <bndbox>
      <xmin>495</xmin>
      <ymin>521</ymin>
      <xmax>519</xmax>
      <ymax>578</ymax>
    </bndbox>
    <confidence>0.451295</confidence>
  </object>
  <object>
    <name>Vehicle</name>
    <bndbox>
      <xmin>843</xmin>
      <ymin>522</ymin>
      <xmax>868</xmax>
      <ymax>546</ymax>
    </bndbox>
    <confidence>0.536951</confidence>
  </object>
  <object>
    <name>Vehicle</name>
    <bndbox>
      <xmin>862</xmin>
      <ymin>518</ymin>
      <xmax>891</xmax>
      <ymax>548</ymax>
    </bndbox>
    <confidence>0.858917</confidence>
  </object>
  <object>
    <name>Vehicle</name>
    <bndbox>
      <xmin>970</xmin>
      <ymin>515</ymin>
      <xmax>1011</xmax>
      <ymax>548</ymax>
    </bndbox>
    <confidence>0.885598</confidence>
  </object>
  <object>
    <name>TrafficSign</name>
    <bndbox>
      <xmin>1784</xmin>
      <ymin>265</ymin>
      <xmax>1851</xmax>
      <ymax>334</ymax>
    </bndbox>
    <confidence>0.927771</confidence>
  </object>
  <object>
    <name>Vehicle</name>
    <bndbox>
      <xmin>883</xmin>
      <ymin>502</ymin>
      <xmax>973</xmax>
      <ymax>570</ymax>
    </bndbox>
    <confidence>0.949041</confidence>
  </object>
  <object>
    <name>Vehicle</name>
    <bndbox>
      <xmin>996</xmin>
      <ymin>490</ymin>
      <xmax>1167</xmax>
      <ymax>621</ymax>
    </bndbox>
    <confidence>0.967643</confidence>
  </object>
  <object>
    <name>Vehicle</name>
    <bndbox>
      <xmin>513</xmin>
      <ymin>241</ymin>
      <xmax>847</xmax>
      <ymax>707</ymax>
    </bndbox>
    <confidence>0.974208</confidence>
  </object>
</annotation>
