<annotation>
  <object>
    <name>Vehicle</name>
    <bndbox>
      <xmin>333</xmin>
      <ymin>549</ymin>
      <xmax>363</xmax>
      <ymax>571</ymax>
    </bndbox>
    <confidence>0.683564</confidence>
  </object>
  <object>
    <name>Vehicle</name>
    <bndbox>
      <xmin>434</xmin>
      <ymin>547</ymin>
      <xmax>463</xmax>
      <ymax>573</ymax>
    </bndbox>
    <confidence>0.779892</confidence>
  </object>
  <object>
    <name>Vehicle</name>
    <bndbox>
      <xmin>362</xmin>
      <ymin>533</ymin>
      <xmax>403</xmax>
      <ymax>576</ymax>
    </bndbox>
    <confidence>0.798048</confidence>
  </object>
  <object>
    <name>Vehicle</name>
    <bndbox>
      <xmin>284</xmin>
      <ymin>541</ymin>
      <xmax>319</xmax>
      <ymax>575</ymax>
    </bndbox>
    <confidence>0.879058</confidence>
  </object>
  <object>
    <name>Vehicle</name>
    <bndbox>
      <xmin>262</xmin>
      <ymin>548</ymin>
      <xmax>301</xmax>
      <ymax>578</ymax>
    </bndbox>
    <confidence>0.893968</confidence>
  </object>
  <object>
    <name>TrafficSign</name>
    <bndbox>
      <xmin>1133</xmin>
      <ymin>407</ymin>
      <xmax>1168</xmax>
      <ymax>448</ymax>
    </bndbox>
    <confidence>0.907502</confidence>
  </object>
  <object>
    <name>TrafficSign</name>
    <bndbox>
      <xmin>1557</xmin>
      <ymin>248</ymin>
      <xmax>1630</xmax>
      <ymax>318</ymax>
    </bndbox>
    <confidence>0.945119</confidence>
  </object>
  <object>
    <name>Vehicle</name>
    <bndbox>
      <xmin>560</xmin>
      <ymin>492</ymin>
      <xmax>673</xmax>
      <ymax>583</ymax>
    </bndbox>
    <confidence>0.959888</confidence>
  </object>
</annotation>
