<annotation>
  <object>
    <name>TrafficSign</name>
    <bndbox>
      <xmin>1361</xmin>
      <ymin>166</ymin>
      <xmax>1501</xmax>
      <ymax>231</ymax>
    </bndbox>
    <confidence>0.750682</confidence>
  </object>
  <object>
    <name>TrafficSign</name>
    <bndbox>
      <xmin>753</xmin>
      <ymin>334</ymin>
      <xmax>783</xmax>
      <ymax>362</ymax>
    </bndbox>
    <confidence>0.839294</confidence>
  </object>
  <object>
    <name>TrafficSign</name>
    <bndbox>
      <xmin>818</xmin>
      <ymin>339</ymin>
      <xmax>847</xmax>
      <ymax>368</ymax>
    </bndbox>
    <confidence>0.895534</confidence>
  </object>
  <object>
    <name>TrafficSign</name>
    <bndbox>
      <xmin>784</xmin>
      <ymin>330</ymin>
      <xmax>818</xmax>
      <ymax>361</ymax>
    </bndbox>
    <confidence>0.900627</confidence>
  </object>
  <object>
    <name>Vehicle</name>
    <bndbox>
      <xmin>893</xmin>
      <ymin>493</ymin>
      <xmax>961</xmax>
      <ymax>545</ymax>
    </bndbox>
    <confidence>0.938657</confidence>
  </object>
</annotation>
