<annotation>
  <object>
    <name>Vehicle</name>
    <bndbox>
      <xmin>562</xmin>
      <ymin>450</ymin>
      <xmax>625</xmax>
      <ymax>518</ymax>
    </bndbox>
    <confidence>0.26754</confidence>
  </object>
  <object>
    <name>Vehicle</name>
    <bndbox>
      <xmin>827</xmin>
      <ymin>479</ymin>
      <xmax>859</xmax>
      <ymax>531</ymax>
    </bndbox>
    <confidence>0.665708</confidence>
  </object>
  <object>
    <name>Vehicle</name>
    <bndbox>
      <xmin>755</xmin>
      <ymin>490</ymin>
      <xmax>790</xmax>
      <ymax>522</ymax>
    </bndbox>
    <confidence>0.786102</confidence>
  </object>
  <object>
    <name>Vehicle</name>
    <bndbox>
      <xmin>609</xmin>
      <ymin>489</ymin>
      <xmax>672</xmax>
      <ymax>531</ymax>
    </bndbox>
    <confidence>0.791857</confidence>
  </object>
  <object>
    <name>Vehicle</name>
    <bndbox>
      <xmin>524</xmin>
      <ymin>493</ymin>
      <xmax>588</xmax>
      <ymax>537</ymax>
    </bndbox>
    <confidence>0.855213</confidence>
  </object>
  <object>
    <name>TrafficSign</name>
    <bndbox>
      <xmin>1751</xmin>
      <ymin>395</ymin>
      <xmax>1803</xmax>
      <ymax>450</ymax>
    </bndbox>
    <confidence>0.90068</confidence>
  </object>
  <object>
    <name>TrafficSign</name>
    <bndbox>
      <xmin>1752</xmin>
      <ymin>339</ymin>
      <xmax>1799</xmax>
      <ymax>391</ymax>
    </bndbox>
    <confidence>0.922927</confidence>
  </object>
  <object>
    <name>Vehicle</name>
    <bndbox>
      <xmin>1000</xmin>
      <ymin>363</ymin>
      <xmax>1156</xmax>
      <ymax>561</ymax>
    </bndbox>
    <confidence>0.943625</confidence>
  </object>
  <object>
    <name>Vehicle</name>
    <bndbox>
      <xmin>1132</xmin>
      <ymin>253</ymin>
      <xmax>1476</xmax>
      <ymax>623</ymax>
    </bndbox>
    <confidence>0.960939</confidence>
  </object>
  <object>
    <name>Vehicle</name>
    <bndbox>
      <xmin>802</xmin>
      <ymin>466</ymin>
      <xmax>1102</xmax>
      <ymax>702</ymax>
    </bndbox>
    <confidence>0.966906</confidence>
  </object>
</annotation>
