<annotation>
  <object>
    <name>Vehicle</name>
    <bndbox>
      <xmin>627</xmin>
      <ymin>551</ymin>
      <xmax>681</xmax>
      <ymax>587</ymax>
    </bndbox>
    <confidence>0.756606</confidence>
  </object>
  <object>
    <name>Vehicle</name>
    <bndbox>
      <xmin>992</xmin>
      <ymin>540</ymin>
      <xmax>1026</xmax>
      <ymax>577</ymax>
    </bndbox>
    <confidence>0.904018</confidence>
  </object>
  <object>
    <name>TrafficSign</name>
    <bndbox>
      <xmin>804</xmin>
      <ymin>157</ymin>
      <xmax>873</xmax>
      <ymax>217</ymax>
    </bndbox>
    <confidence>0.935869</confidence>
  </object>
</annotation>
