<annotation>
  <object>
    <name>Vehicle</name>
    <bndbox>
      <xmin>981</xmin>
      <ymin>529</ymin>
      <xmax>1018</xmax>
      <ymax>557</ymax>
    </bndbox>
    <confidence>0.666117</confidence>
  </object>
  <object>
    <name>Vehicle</name>
    <bndbox>
      <xmin>508</xmin>
      <ymin>527</ymin>
      <xmax>691</xmax>
      <ymax>593</ymax>
    </bndbox>
    <confidence>0.895083</confidence>
  </object>
  <object>
    <name>Vehicle</name>
    <bndbox>
      <xmin>1085</xmin>
      <ymin>519</ymin>
      <xmax>1131</xmax>
      <ymax>576</ymax>
    </bndbox>
    <confidence>0.914531</confidence>
  </object>
  <object>
    <name>TrafficSign</name>
    <bndbox>
      <xmin>1561</xmin>
      <ymin>373</ymin>
      <xmax>1618</xmax>
      <ymax>449</ymax>
    </bndbox>
    <confidence>0.923385</confidence>
  </object>
  <object>
    <name>TrafficSign</name>
    <bndbox>
      <xmin>1141</xmin>
      <ymin>78</ymin>
      <xmax>1222</xmax>
      <ymax>152</ymax>
    </bndbox>
    <confidence>0.940499</confidence>
  </object>
  <object>
    <name>Vehicle</name>
    <bndbox>
      <xmin>941</xmin>
      <ymin>538</ymin>
      <xmax>1022</xmax>
      <ymax>602</ymax>
    </bndbox>
    <confidence>0.942617</confidence>
  </object>
</annotation>
